<?xml version="1.0" encoding="utf-8" ?>
<hibernate-mapping xmlns="urn:nhibernate-mapping-2.2">
   <class name="Arashi.Core.Domain.PagePermission, Arashi.Core.Domain" 
       table="cms_PageRoles" >

      <!--<cache usage="read-write" />-->

      <id name="Id" column="PageRoleId" type="Int32" unsaved-value="-1">
         <generator class="hilo"/>
      </id>

      <property name="ViewAllowed" column="ViewAllowed" type="Boolean" not-null="true" />
      <property name="EditAllowed" column="EditAllowed" type="Boolean" not-null="true" />
      <property name="DeleteAllowed" column="DeleteAllowed" type="Boolean" not-null="true" />
      <many-to-one name="Role" class="Arashi.Core.Domain.Role, Arashi.Core.Domain" column="RoleId" cascade="none" not-null="true" />
      <many-to-one name="Page" class="Arashi.Core.Domain.Page, Arashi.Core.Domain" column="PageId" cascade="none" not-null="true" />

   </class>
</hibernate-mapping>